openrouter/__init__.py
openrouter/client.py
openrouter/core/__init__.py
openrouter/core/config.py
openrouter/models/__init__.py
openrouter/models/helpers.py
openrouter/models/request.py
openrouter/models/response.py
openrouter_client-0.1.0.dist-info/AUTHORS
openrouter_client-0.1.0.dist-info/LICENSE
openrouter_client-0.1.0.dist-info/METADATA
openrouter_client-0.1.0.dist-info/WHEEL
openrouter_client-0.1.0.dist-info/top_level.txt
openrouter_client-0.1.0.dist-info/RECORD
