Metadata-Version: 2.1
Name: openrouter-client
Version: 0.1.0
Summary: OpenRouter API client library
Home-page: https://github.com/mrcodepanda/openrouter-client
Author: Sudhanshu Aggarwal (@mrcodepanda)
Author-email: "Sudhanshu Aggarwal (@mrcodepanda)" <mrcodepanda@refactors.io>
License: GPL-3.0-or-later
Project-URL: Homepage, https://github.com/mrcodepanda/openrouter-client
Project-URL: Bug Tracker, https://github.com/mrcodepanda/openrouter-client/issues
Project-URL: Source Code, https://github.com/mrcodepanda/openrouter-client
Classifier: Development Status :: 3 - Alpha
Classifier: Intended Audience :: Developers
Classifier: License :: OSI Approved :: GNU General Public License v3 or later (GPLv3+)
Classifier: Programming Language :: Python :: 3
Classifier: Programming Language :: Python :: 3.8
Classifier: Programming Language :: Python :: 3.9
Classifier: Programming Language :: Python :: 3.10
Requires-Python: >=3.8
License-File: LICENSE
License-File: AUTHORS
Requires-Dist: httpx>=0.24.1
Requires-Dist: fastapi>=0.100.0
Requires-Dist: pydantic>=2.0.2
Requires-Dist: pydantic-settings>=2.0.2
Requires-Dist: python-dotenv>=1.0.0
Provides-Extra: dev
Requires-Dist: pytest>=7.3.1; extra == "dev"
Requires-Dist: pytest-asyncio>=0.21.0; extra == "dev"
Requires-Dist: pytest-cov>=4.1.0; extra == "dev"
Requires-Dist: setuptools>=75.3.2; extra == "dev"
Requires-Dist: twine>=6.1.0; extra == "dev"
